{
	"configurations" : 
	[
		{
			"directories" : 
			[
				{
					"build" : ".",
					"jsonFile" : "directory-.-Debug-d0094a50bb2071803777.json",
					"minimumCMakeVersion" : 
					{
						"string" : "3.28"
					},
					"projectIndex" : 0,
					"source" : ".",
					"targetIndexes" : 
					[
						0,
						1,
						2,
						3,
						4,
						5
					]
				}
			],
			"name" : "Debug",
			"projects" : 
			[
				{
					"directoryIndexes" : 
					[
						0
					],
					"name" : "DAACODING",
					"targetIndexes" : 
					[
						0,
						1,
						2,
						3,
						4,
						5
					]
				}
			],
			"targets" : 
			[
				{
					"directoryIndex" : 0,
					"id" : "GRAPHMATRIX::@6890427a1f51a3e7e1df",
					"jsonFile" : "target-GRAPHMATRIX-Debug-a53e04bd682642081fc3.json",
					"name" : "GRAPHMATRIX",
					"projectIndex" : 0
				},
				{
					"directoryIndex" : 0,
					"id" : "HASHTABLE::@6890427a1f51a3e7e1df",
					"jsonFile" : "target-HASHTABLE-Debug-24ef9462482f3573d1ff.json",
					"name" : "HASHTABLE",
					"projectIndex" : 0
				},
				{
					"directoryIndex" : 0,
					"id" : "QUICKSORT::@6890427a1f51a3e7e1df",
					"jsonFile" : "target-QUICKSORT-Debug-3c58ca39e02292713de3.json",
					"name" : "QUICKSORT",
					"projectIndex" : 0
				},
				{
					"directoryIndex" : 0,
					"id" : "REDLACK::@6890427a1f51a3e7e1df",
					"jsonFile" : "target-REDLACK-Debug-b3a49001836287862904.json",
					"name" : "REDLACK",
					"projectIndex" : 0
				},
				{
					"directoryIndex" : 0,
					"id" : "SHORTESTPATH::@6890427a1f51a3e7e1df",
					"jsonFile" : "target-SHORTESTPATH-Debug-cfc83328fbcbcf13cc95.json",
					"name" : "SHORTESTPATH",
					"projectIndex" : 0
				},
				{
					"directoryIndex" : 0,
					"id" : "SPLAYTREE::@6890427a1f51a3e7e1df",
					"jsonFile" : "target-SPLAYTREE-Debug-effbfd0ab713a4ddb8de.json",
					"name" : "SPLAYTREE",
					"projectIndex" : 0
				}
			]
		}
	],
	"kind" : "codemodel",
	"paths" : 
	{
		"build" : "C:/Users/Jeecoo/DAACODING/cmake-build-debug",
		"source" : "C:/Users/Jeecoo/DAACODING"
	},
	"version" : 
	{
		"major" : 2,
		"minor" : 6
	}
}
